cffconvert/__init__.py
cffconvert/citation.py
cffconvert/root.py
cffconvert/version.py
cffconvert/behavior_1_0_x/__init__.py
cffconvert/behavior_1_0_x/apalike_author.py
cffconvert/behavior_1_0_x/apalike_object.py
cffconvert/behavior_1_0_x/apalike_url.py
cffconvert/behavior_1_0_x/bibtex_author.py
cffconvert/behavior_1_0_x/bibtex_object.py
cffconvert/behavior_1_0_x/bibtex_url.py
cffconvert/behavior_1_0_x/citation.py
cffconvert/behavior_1_0_x/codemeta_object.py
cffconvert/behavior_1_0_x/endnote_author.py
cffconvert/behavior_1_0_x/endnote_object.py
cffconvert/behavior_1_0_x/endnote_url.py
cffconvert/behavior_1_0_x/ris_author.py
cffconvert/behavior_1_0_x/ris_object.py
cffconvert/behavior_1_0_x/ris_url.py
cffconvert/behavior_1_0_x/schemaorg_author.py
cffconvert/behavior_1_0_x/schemaorg_object.py
cffconvert/behavior_1_0_x/schemaorg_urls.py
cffconvert/behavior_1_0_x/zenodo_creator.py
cffconvert/behavior_1_0_x/zenodo_object.py
cffconvert/behavior_1_1_x/__init__.py
cffconvert/behavior_1_1_x/apalike_author.py
cffconvert/behavior_1_1_x/apalike_object.py
cffconvert/behavior_1_1_x/apalike_url.py
cffconvert/behavior_1_1_x/bibtex_author.py
cffconvert/behavior_1_1_x/bibtex_object.py
cffconvert/behavior_1_1_x/bibtex_url.py
cffconvert/behavior_1_1_x/citation.py
cffconvert/behavior_1_1_x/codemeta_object.py
cffconvert/behavior_1_1_x/endnote_author.py
cffconvert/behavior_1_1_x/endnote_object.py
cffconvert/behavior_1_1_x/endnote_url.py
cffconvert/behavior_1_1_x/ris_author.py
cffconvert/behavior_1_1_x/ris_object.py
cffconvert/behavior_1_1_x/ris_url.py
cffconvert/behavior_1_1_x/schemaorg_author.py
cffconvert/behavior_1_1_x/schemaorg_object.py
cffconvert/behavior_1_1_x/schemaorg_urls.py
cffconvert/behavior_1_1_x/zenodo_creator.py
cffconvert/behavior_1_1_x/zenodo_object.py
cffconvert/behavior_1_2_x/__init__.py
cffconvert/behavior_1_2_x/apalike_author.py
cffconvert/behavior_1_2_x/apalike_object.py
cffconvert/behavior_1_2_x/apalike_url.py
cffconvert/behavior_1_2_x/bibtex_author.py
cffconvert-2.0.0.dist-info/LICENSE
cffconvert-2.0.0.dist-info/METADATA
cffconvert-2.0.0.dist-info/WHEEL
cffconvert-2.0.0.dist-info/entry_points.txt
cffconvert-2.0.0.dist-info/top_level.txt
cffconvert-2.0.0.dist-info/RECORD
