Metadata-Version: 2.1
Name: cffconvert
Version: 2.0.0
Summary: Command line program to validate and convert CITATION.cff files.
Home-page: https://github.com/citation-file-format/cff-converter-python
Author: Jurriaan H. Spaaks
Author-email: j.spaaks@esciencecenter.nl
License: UNKNOWN
Project-URL: Bug Tracker, https://github.com/citation-file-format/cff-converter-python/issues
Project-URL: Source, https://github.com/citation-file-format/cff-converter-python
Keywords: citation,credit,CITATION.cff,BibTeX,EndNote,RIS,CodeMeta,Zenodo
Platform: UNKNOWN
Classifier: Development Status :: 5 - Production/Stable
Classifier: Intended Audience :: Developers
Classifier: Intended Audience :: Education
Classifier: Intended Audience :: Information Technology
Classifier: Intended Audience :: Science/Research
Classifier: Intended Audience :: System Administrators
Classifier: License :: OSI Approved :: Apache Software License
Classifier: Natural Language :: English
Classifier: Programming Language :: Python :: 3
Classifier: Programming Language :: Python :: 3.6
Classifier: Programming Language :: Python :: 3.7
Classifier: Programming Language :: Python :: 3.8
Classifier: Programming Language :: Python :: 3.9
Classifier: Topic :: Scientific/Engineering
Classifier: Topic :: Software Development
Classifier: Topic :: Utilities
Provides-Extra: dev
Provides-Extra: publishing
Provides-Extra: gcloud
License-File: LICENSE
